MANIFEST.in
account_followup_customers.xml
account_followup_data.xml
account_followup_demo.xml
account_followup_view.xml
setup.py
./__init__.py
./__openerp__.py
./account_followup.py
./report/__init__.py
./report/account_followup_print.py
./report/account_followup_report.py
./tests/__init__.py
./tests/test_account_followup.py
./wizard/__init__.py
./wizard/account_followup_print.py
i18n/account_followup.pot
i18n/ar.po
i18n/bg.po
i18n/bs.po
i18n/ca.po
i18n/cs.po
i18n/da.po
i18n/de.po
i18n/el.po
i18n/en_GB.po
i18n/es.po
i18n/es_AR.po
i18n/es_CR.po
i18n/es_EC.po
i18n/es_MX.po
i18n/es_PY.po
i18n/es_VE.po
i18n/et.po
i18n/fa.po
i18n/fi.po
i18n/fr.po
i18n/gl.po
i18n/hr.po
i18n/hu.po
i18n/id.po
i18n/it.po
i18n/ja.po
i18n/ko.po
i18n/lt.po
i18n/mk.po
i18n/mn.po
i18n/nb.po
i18n/nl.po
i18n/nl_BE.po
i18n/oc.po
i18n/pl.po
i18n/pt.po
i18n/pt_BR.po
i18n/ro.po
i18n/ru.po
i18n/sl.po
i18n/sq.po
i18n/sr.po
i18n/sr@latin.po
i18n/sv.po
i18n/tlh.po
i18n/tr.po
i18n/uk.po
i18n/vi.po
i18n/zh_CN.po
i18n/zh_TW.po
images/follow_ups.jpeg
images/send_followups.jpeg
openerp_account_followup.egg-info/PKG-INFO
openerp_account_followup.egg-info/SOURCES.txt
openerp_account_followup.egg-info/dependency_links.txt
openerp_account_followup.egg-info/requires.txt
openerp_account_followup.egg-info/top_level.txt
report/account_followup_print.rml
report/account_followup_print.sxw
report/account_followup_report.xml
security/account_followup_security.xml
security/ir.model.access.csv
test/account_followup.yml
wizard/account_followup_print_view.xml